{
  "component_reviewer_version": 1,
  "checks": [
    {
      "audit_check_id": "deb-installed-version",
      "outcome": "issue",
      "finding_kind": "security",
      "severity": "high",
      "detail": "Routed security issue."
    },
    {
      "audit_check_id": "installer-validated-staleness",
      "outcome": "issue",
      "finding_kind": "staleness",
      "detail": "Routed freshness issue."
    }
  ],
  "build": "fixture-review",
  "component": "issue-routed",
  "review_completed": "2026-05-09T14:28:59Z",
  "concerns": {
    "security": true,
    "freshness": true,
    "skipped": false,
    "incomplete": false
  }
}
